{"cartridge": [
    {
        "activeInstances": 0,
        "cartridgeAlias": "-",
        "cartridgeType": "lb",
        "description": "LB Cartridge",
        "displayName": "load balancer",
        "multiTenant": false,
        "provider": "apache",
        "status": "NOT-SUBSCRIBED",
        "version": 4
    },
    {
        "activeInstances": 0,
        "cartridgeAlias": "-",
        "cartridgeType": "php",
        "description": "Apache Stratos PHP Cartridge",
        "displayName": "Apache Stratos PHP Cartridge",
        "multiTenant": false,
        "provider": "Apache Stratos",
        "status": "NOT-SUBSCRIBED",
        "version": 1
    },
    {
        "activeInstances": 0,
        "cartridgeAlias": "-",
        "cartridgeType": "stratos-lb",
        "description": "Apache Stratos Load Balancer Cartridge",
        "displayName": "Apache Stratos Load Balancer Cartridge",
        "multiTenant": false,
        "provider": "apache",
        "status": "NOT-SUBSCRIBED",
        "version": 4
    }
]}